HISTORY.rst
LICENSE
MANIFEST.in
README.rst
setup.cfg
setup.py
django_akismet_comments/__init__.py
django_akismet_comments.egg-info/PKG-INFO
django_akismet_comments.egg-info/SOURCES.txt
django_akismet_comments.egg-info/dependency_links.txt
django_akismet_comments.egg-info/entry_points.txt
django_akismet_comments.egg-info/not-zip-safe
django_akismet_comments.egg-info/requires.txt
django_akismet_comments.egg-info/top_level.txt