Metadata-Version: 1.1
Name: django-akismet-comments
Version: 0.1
Summary: Django moderator for checking django.contrib.comments spam against akismet service.
Home-page: UNKNOWN
Author: Domen Kožar
Author-email: domen@dev.si
License: BSD
Platform: UNKNOWN
Classifier: Programming Language :: Python
